rumorpheme/__init__.py
rumorpheme/const.py
rumorpheme/model.py
rumorpheme/tokenizer.py
rumorpheme/utils/__init__.py
rumorpheme/utils/labels_to_morphemes.py
rumorpheme/utils/prepare_data.py
ruMorpheme-0.3.0.dist-info/LICENSE
ruMorpheme-0.3.0.dist-info/METADATA
ruMorpheme-0.3.0.dist-info/WHEEL
ruMorpheme-0.3.0.dist-info/top_level.txt
ruMorpheme-0.3.0.dist-info/RECORD
