Metadata-Version: 2.1
Name: ruMorpheme
Version: 0.3.0
Summary: Проект языковой модели для проведения морфемного анализа и сегментации слов русского языка.
Home-page: https://github.com/EvilFreelancer/ruMorpheme
Author: Pavel Rykov
Author-email: paul@drteam.rocks
Keywords: natural language processing,nlp,morpheme,russian
Classifier: Programming Language :: Python :: 3
Classifier: License :: OSI Approved :: MIT License
Classifier: Operating System :: OS Independent
Classifier: Intended Audience :: Developers
Classifier: Intended Audience :: Science/Research
Classifier: Topic :: Scientific/Engineering :: Artificial Intelligence
Classifier: Topic :: Software Development :: Libraries :: Python Modules
Classifier: Topic :: Scientific/Engineering :: Information Analysis
Classifier: Topic :: Text Processing :: Linguistic
Classifier: Natural Language :: Russian
Requires-Python: >=3.11
License-File: LICENSE
Requires-Dist: numpy~=2.1.1
Requires-Dist: torch~=2.4.1
Requires-Dist: huggingface-hub~=0.25.1
